{"stats":{"minecraft:picked_up":{"minecraft:wooden_axe":1,"minecraft:birch_log":9,"minecraft:stick":6,"minecraft:crafting_table":2,"minecraft:pumpkin":1,"minecraft:feather":1,"minecraft:chicken":2,"forbidden_arcanus:tentacle":1,"minecraft:wooden_pickaxe":1,"minecraft:gravel":1,"alexsmobs:cachalot_whale_tooth":2,"minecraft:oak_log":23,"minecraft:ink_sac":7,"crittersandcompanions:grappling_hook":1,"minecraft:white_bed":2,"minecraft:spider_eye":3,"minecraft:dirt":1,"minecraft:bone":5,"minecraft:apple":1,"minecraft:wheat_seeds":2,"crittersandcompanions:silk":3,"minecraft:bone_meal":2,"minecraft:oak_boat":3,"minecraft:bread":18,"minecraft:iron_nugget":1,"minecraft:oak_sapling":11,"minecraft:birch_sapling":1,"minecraft:coal":19,"iceandfire:raw_silver":3,"minecraft:cobblestone":28},"minecraft:killed_by":{"alexsmobs:grizzly_bear":2},"minecraft:dropped":{"minecraft:wooden_axe":1,"minecraft:wooden_pickaxe":1,"crittersandcompanions:silk":3},"minecraft:custom":{"minecraft:time_since_rest":920,"minecraft:sprint_one_cm":189930,"minecraft:damage_taken":750,"minecraft:walk_one_cm":282075,"minecraft:mob_kills":5,"minecraft:drop":3,"minecraft:damage_dealt":714,"minecraft:interact_with_crafting_table":8,"minecraft:swim_one_cm":27793,"minecraft:fly_one_cm":83620,"minecraft:crouch_one_cm":4662,"minecraft:play_time":34158,"minecraft:deaths":2,"minecraft:sneak_time":598,"minecraft:walk_under_water_one_cm":5938,"minecraft:boat_one_cm":32035,"minecraft:jump":460,"minecraft:time_since_death":888,"minecraft:walk_on_water_one_cm":15280,"minecraft:sleep_in_bed":6,"minecraft:total_world_time":34158,"minecraft:fall_one_cm":7884},"minecraft:killed":{"minecraft:chicken":2,"grimoireofgaia:harpy":1,"naturalist:snail":2},"minecraft:used":{"minecraft:wooden_axe":19,"minecraft:apple":1,"minecraft:stone_sword":17,"minecraft:bread":8,"minecraft:stone_pickaxe":36,"minecraft:wooden_pickaxe":13,"minecraft:stone_axe":2,"minecraft:crafting_table":3,"minecraft:white_bed":1,"minecraft:oak_boat":3,"alexsmobs:animal_dictionary":1},"minecraft:crafted":{"minecraft:oak_planks":12,"minecraft:crafting_table":1,"minecraft:stick":4,"minecraft:wooden_pickaxe":1,"minecraft:stone_pickaxe":1,"minecraft:wooden_axe":1,"minecraft:stone_sword":1,"minecraft:birch_planks":4,"minecraft:stone_axe":1},"minecraft:mined":{"minecraft:white_bed":2,"brewery:wild_hops":1,"iceandfire:silver_ore":3,"minecraft:birch_log":1,"minecraft:pumpkin":1,"treechop:chopped_log":5,"minecraft:crafting_table":2,"mirabilis:grass_pile":1,"realmrpg_skeletons:devastated_skeleton":1,"minecraft:grass":3,"minecraft:coal_ore":18,"minecraft:grass_block":1,"minecraft:oak_log":1,"minecraft:gravel":1,"minecraft:stone":27}},"DataVersion":3465}