{"stats":{"minecraft:broken":{"minecraft:stone_pickaxe":1,"minecraft:stone_axe":1},"minecraft:picked_up":{"minecraft:iron_chestplate":1,"minecraft:crafting_table":6,"minecraft:wheat":10,"gravestone:obituary":2,"minecraft:brewing_stand":2,"minecraft:cornflower":1,"minecraft:string":3,"minecraft:raw_copper":6,"iter_rpg:etherbloom":2,"minecraft:beetroot":53,"bloodandmadness:blood_vial":2,"minecraft:gold_nugget":1,"minecraft:cobbled_deepslate":2,"minecraft:oak_boat":1,"minecraft:rose_bush":1,"minecraft:iron_nugget":3,"minecraft:poppy":3,"minecraft:sugar_cane":21,"minecraft:chest":1,"minecraft:egg":2,"minecraft:raw_iron":38,"minecraft:stick":3,"minecraft:torch":62,"epicfight:skillbook":1,"minecraft:carrot":2,"minecraft:redstone":26,"minecraft:arrow":2,"minecraft:rotten_flesh":2,"minecraft:beetroot_seeds":14,"minecraft:hay_block":13,"crittersandcompanions:silk":6,"farm_and_charm:strawberry":12,"minecraft:mutton":2,"bloodandmadness:blood_stone_shard":1,"minecraft:white_wool":1,"minecraft:cobblestone":46,"minecraft:feather":3,"minecraft:glow_ink_sac":3,"minecraft:potato":51,"minecraft:oak_log":53,"evilcraft:flesh_humanoid":1,"iceandfire:ectoplasm":2,"minecraft:gunpowder":4,"minecraft:lapis_lazuli":74,"minecraft:dirt":3,"brewery:hops_seeds":4,"minecraft:bone":8,"minecraft:bow":1,"minecraft:wheat_seeds":2,"minecraft:stone_pickaxe":1,"minecraft:iron_ingot":18,"minecraft:oak_planks":16,"minecraft:book":24,"minecraft:sweet_berries":36,"epicfight:uchigatana":1,"minecraft:white_bed":7,"minecraft:spider_eye":1,"forbidden_arcanus:arcane_crystal":1,"minecraft:slime_ball":2,"waystones:waystone":2,"iter_rpg:abyssquartz_shard":4,"evilcraft:dark_gem":22,"minecraft:gray_wool":20,"minecraft:bread":1,"minecraft:oak_sapling":12,"minecraft:coal":40},"minecraft:killed_by":{"minecraft:warden":1,"grimoireofgaia:deathword":1,"minecraft:skeleton":1,"grimoireofgaia:nine_tails":1,"iceandfire:ghost":3},"minecraft:dropped":{"minecraft:bread":18,"minecraft:wheat_seeds":1,"minecraft:feather":3,"iter_rpg:etherbloom":1,"minecraft:cornflower":1,"minecraft:mutton":2,"minecraft:gold_nugget":1,"minecraft:iron_leggings":1,"gravestone:obituary":11,"minecraft:white_wool":1,"minecraft:bone":2,"epicfight:uchigatana":1,"minecraft:raw_copper":3,"brewery:potato_salad":32,"minecraft:rotten_flesh":2,"minecraft:iron_boots":1,"minecraft:oak_planks":16,"evilcraft:origins_of_darkness":1,"minecraft:poppy":2,"minecraft:shield":1,"minecraft:gunpowder":1,"minecraft:iron_chestplate":2,"minecraft:oak_boat":1,"minecraft:spider_eye":1,"minecraft:bow":1,"bloodandmadness:blood_stone_shard":1,"minecraft:stone_pickaxe":1,"crittersandcompanions:grappling_hook":1,"epicfight:skillbook":3},"minecraft:custom":{"minecraft:mob_kills":35,"minecraft:interact_with_crafting_table":28,"minecraft:time_since_death":4871,"minecraft:climb_one_cm":4292,"minecraft:sprint_one_cm":582237,"minecraft:walk_one_cm":1150935,"minecraft:damage_blocked_by_shield":90,"minecraft:drop":55,"minecraft:damage_dealt_absorbed":168,"minecraft:talked_to_villager":4,"minecraft:play_time":171614,"minecraft:deaths":9,"minecraft:sneak_time":14555,"minecraft:walk_under_water_one_cm":19832,"minecraft:boat_one_cm":64725,"minecraft:jump":3145,"minecraft:walk_on_water_one_cm":88446,"minecraft:total_world_time":171614,"minecraft:interact_with_furnace":25,"minecraft:sleep_in_bed":18,"minecraft:time_since_rest":4902,"minecraft:waystone_activated":1,"minecraft:damage_taken":4075,"minecraft:trigger_trapped_chest":2,"minecraft:damage_dealt":11622,"minecraft:swim_one_cm":29931,"minecraft:fly_one_cm":1092360,"minecraft:open_chest":61,"minecraft:crouch_one_cm":48811,"minecraft:fall_one_cm":86916},"minecraft:killed":{"minecraft:spider":3,"minecraft:skeleton":4,"grimoireofgaia:creep":1,"grimoireofgaia:flesh_lich":1,"grimoireofgaia:cyan_flower":3,"minecraft:pig":1,"minecraft:iron_golem":4,"minecraft:creeper":2,"grimoireofgaia:oni":1,"minecraft:sheep":2,"minecraft:pillager":2,"minecraft:zombie":3,"iceandfire:ghost":4,"grimoireofgaia:harpy":2,"alexsmobs:crow":1,"grimoireofgaia:kobold":1},"minecraft:used":{"minecraft:rose_bush":1,"minecraft:poppy":1,"minecraft:chest":3,"minecraft:shield":3,"minecraft:iron_chestplate":1,"minecraft:torch":34,"minecraft:dirt":3,"minecraft:carrot":2,"spartanweaponry:iron_rapier":16,"minecraft:sweet_berries":39,"minecraft:furnace":3,"minecraft:egg":2,"minecraft:iron_leggings":1,"minecraft:wheat_seeds":1,"epicfight:skillbook":4,"brewery:potato_salad":7,"minecraft:stone_pickaxe":177,"minecraft:oak_planks":18,"minecraft:wooden_pickaxe":4,"spartanweaponry:wooden_longbow":4,"farm_and_charm:strawberry":10,"minecraft:crafting_table":8,"minecraft:white_bed":7,"waystones:waystone":1,"minecraft:iron_pickaxe":30,"minecraft:bread":31,"minecraft:stone_axe":81,"minecraft:cobblestone":7,"minecraft:oak_boat":2,"minecraft:gray_wool":3,"epicfight:uchigatana":73},"minecraft:crafted":{"minecraft:oak_planks":104,"brewery:potato_salad":96,"minecraft:furnace":3,"minecraft:iron_boots":2,"minecraft:stone_pickaxe":2,"minecraft:chest":2,"crittersandcompanions:grappling_hook":1,"minecraft:wheat":117,"minecraft:crafting_table":2,"minecraft:wooden_pickaxe":1,"minecraft:baked_potato":24,"spartanweaponry:handle":1,"spartanweaponry:iron_rapier":1,"minecraft:stone_axe":2,"minecraft:bread":42,"minecraft:air":0,"minecraft:oak_boat":3,"minecraft:iron_chestplate":2,"minecraft:shield":2,"minecraft:stick":16,"minecraft:iron_pickaxe":1,"minecraft:iron_ingot":31,"minecraft:iron_leggings":2},"minecraft:mined":{"minecraft:white_bed":7,"minecraft:brewing_stand":2,"gravestone:gravestone":8,"minecraft:grass_block":2,"minecraft:hay_block":13,"forbidden_arcanus:deepslate_arcane_crystal_ore":1,"minecraft:carrots":2,"minecraft:iron_ore":23,"iter_rpg:etherbloom":1,"treechop:chopped_log":3,"evilcraft:dark_ore":4,"minecraft:deepslate_lapis_ore":8,"realmrpg_skeletons:devastated_skeleton":1,"realmrpg_skeletons:rookie_skeleton":1,"minecraft:bookshelf":8,"minecraft:potatoes":4,"minecraft:deepslate_iron_ore":15,"crittersandcompanions:silk_cocoon":2,"farm_and_charm:wild_strawberries":4,"mirabilis:oak_leave_carpet":1,"farm_and_charm:wild_emmer":2,"minecraft:stone":33,"minecraft:deepslate_redstone_ore":6,"brewery:wild_hops":2,"farm_and_charm:wild_beetroots":17,"minecraft:crafting_table":6,"farm_and_charm:wild_potatoes":13,"minecraft:chest":1,"minecraft:rose_bush":1,"minecraft:tall_grass":8,"minecraft:cobblestone":12,"minecraft:lapis_ore":4,"minecraft:oak_planks":11,"minecraft:sugar_cane":11,"farmersdelight:wild_beetroots":11,"minecraft:gray_wool":21,"farmersdelight:sandy_shrub":1,"evilcraft:dark_ore_deepslate":1,"iter_rpg:abyss_quartz":3,"minecraft:sweet_berry_bush":16,"biomesoplenty:maple_leaves":3,"minecraft:grass":9,"minecraft:oak_log":1,"minecraft:coal_ore":40,"minecraft:beetroots":1,"minecraft:deepslate":2,"minecraft:oak_leaves":1,"minecraft:fern":2}},"DataVersion":3465}